play_checkers/__init__.py
play_checkers/__main__.py
play_checkers/play.py
play_checkers-1.0.5.dist-info/entry_points.txt
play_checkers-1.0.5.dist-info/WHEEL
play_checkers-1.0.5.dist-info/METADATA
play_checkers-1.0.5.dist-info/RECORD
