Metadata-Version: 2.1
Name: play-checkers
Version: 1.0.5
Summary: Python Checkers Game
License: MIT
Author: Sarcoma
Author-email: sarcoma@live.co.uk
Requires-Python: >=3.6,<4.0
Classifier: License :: OSI Approved :: MIT License
Classifier: Programming Language :: Python :: 3
Classifier: Programming Language :: Python :: 3.6
Classifier: Programming Language :: Python :: 3.7
Classifier: Programming Language :: Python :: 3.8
Classifier: Programming Language :: Python :: 3.9
